<?xml version="1.0" encoding="utf-8"?><?xml-stylesheet type="text/xsl"
		href="file:////valtion.fi/Yhteiset tiedostot/Kotus/verkko-sms/standardimuunnos/isohtml.xsl"
	?>
<!DOCTYPE Dictionary
  SYSTEM "P:\bin\dtd\xmlex\XmLex_V00_kotus_V02.dtd">
<Dictionary xmlns:xlink="http://www.w3.org/TR/xlink" xmlns:kotus="http://www.kotus.fi/" xmlns:fn="http://www.w3.org/2005/xpath-functions" sourceLanguage="suomi" targetLanguage="suomi"><DictionaryEntry id="SMS_cde11c876d7bdb608430670f9191605d" homographNumber="1" style="normaali"><HeadwordCtn><Headword>liina</Headword><SearchForm display="no">liina</SearchForm><PartOfSpeechCtn><PartOfSpeech freeValue="s."/></PartOfSpeechCtn></HeadwordCtn><p style="kappaleenvaihto"/><SeeAlsoBlock><SeeAlso style="Yhd"><Ptr xlink:href="SMS_8a67953048f80b5737a3960aff7b91a2" word="esiliina">esiliina</Ptr><Ptr xlink:href="SMS_c55b5b7a7234e8d5dce864aa3acadde0" word="fapriikinliina">fapriikinliina</Ptr><Ptr xlink:href="SMS_9d8e9829f59c06a5b5d0f2072114d0b9" word="hamppuliina">hamppuliina</Ptr><Ptr xlink:href="SMS_f936eb46552e0baba6d74d0fcf98f76c" word="iholiina">iholiina</Ptr><Ptr xlink:href="SMS_58fd158a2141e50abc85a3e4aacfa329" word="kateliina">kateliina</Ptr><Ptr xlink:href="SMS_a00203f3db0f79b6f177c14171f4d93f" word="kirkkoliina">kirkkoliina</Ptr><Ptr xlink:href="SMS_6c3f950d957dec8ffa04aba73f0efcb9" word="klanssiliina">klanssiliina</Ptr><Ptr xlink:href="SMS_69a10001d2989fbcd06dca95ab83e7af" word="koirasliina">koirasliina</Ptr><Ptr xlink:href="SMS_9eea091125ba160970bc339ecaefa252" word="k%C3%A4siliina">käsiliina</Ptr><Ptr xlink:href="SMS_fdff850bd393715e5440c9d1828b06f0" word="lakanaliina">lakanaliina</Ptr><Ptr xlink:href="SMS_025b434afca24a2f837f85a711bf2724" word="lepp%C3%A4liina">leppäliina</Ptr><Ptr xlink:href="SMS_83db1d671f4af4a2e51eff06603886ef" word="pieniliina">pieniliina</Ptr><Ptr xlink:href="SMS_61adc55f572eb19def25c796fddd3d6b" word="pleikiliina">pleikiliina</Ptr><Ptr xlink:href="SMS_ef22e074d1301d5ed3f7ce75a58db93b" word="pyyhinliina">pyyhinliina</Ptr><Ptr xlink:href="SMS_731cdaf7d882971a287af4f3e65d8dba" word="p%C3%A4%C3%A4liina">pääliina</Ptr><Ptr xlink:href="SMS_7a43053252e1f150fb6b93e181d4dab9" word="vuosiliina">vuosiliina</Ptr><Ptr xlink:href="SMS_b94433c11d01152fe2ad4ee2b0b612ed" word="vy%C3%B6liina">vyöliina</Ptr><Ptr xlink:href="SMS_709ef49a2de4f0a9aaed0e89b00b59a0" word="v%C3%A4liliina">väliliina</Ptr></SeeAlso></SeeAlsoBlock><SenseGrp id="SMS_251482ecb7ff30682e778beb3231f7bb"><Definition>Cannabis sativa, hamppu.</Definition><Ptr style="kartta" xlink:href="98735"/><FreeTopic type="levikkitiedot"><GeographicalUsage type="used" freeType="alue" freeValue="Karjala">Kar</GeographicalUsage><GeographicalUsage type="used" freeType="alue" freeValue="Savo">Sav</GeographicalUsage><GeographicalUsage type="used" freeType="alue" freeValue="pohjoinen Keski-Suomi">KesP</GeographicalUsage>, joitakin tietoja<GeographicalUsage type="used" freeType="alue" freeValue="Kymenlaakso ja Itä-Uusimaa">Kym</GeographicalUsage><GeographicalUsage type="used" freeType="alue" freeValue="eteläinen Keski-Suomi">KesE</GeographicalUsage><GeographicalUsage type="used" freeType="alue" freeValue="Inkeri">Ink</GeographicalUsage> ja liepeiltä.</FreeTopic><ExampleBlock><ExampleCtn><Example style="normal"><Citation style="dialect">Oikei vanhaa aikaa pantii
miehii pöksyloimiks liinaa.</Citation></Example><GeographicalUsage type="used" freeType="pitäjä">Antrea</GeographicalUsage></ExampleCtn><ExampleCtn><Example style="normal"><Citation style="dialect">liina
se o vähä ruovimpaa<Gloss>= karkeasyisempää</Gloss>, järijämpää</Citation>
kuin pellava.</Example><GeographicalUsage type="used" freeType="pitäjä">Uusikirkko Vpl.</GeographicalUsage></ExampleCtn><ExampleCtn><Example style="normal"><Citation style="dialect">kum<Gloss>laskiaisena</Gloss> pitkät mäet laskoo,
pellavat kasvaa ja liinat.</Citation></Example><GeographicalUsage type="used" freeType="pitäjä">Uukuniemi</GeographicalUsage></ExampleCtn><ExampleCtn><Example style="normal"><Citation style="dialect">Liinasta
tul vahvemp̆poo vuatetta</Citation> kuin pellavasta.</Example><GeographicalUsage type="used" freeType="pitäjä">Eno</GeographicalUsage></ExampleCtn><ExampleCtn><Example style="normal">Hamppu
kylvetään viimeiseksi:<Citation style="dialect">se ov viim̆menen tòuko
liin̆na.</Citation></Example><GeographicalUsage type="used" freeType="pitäjä">Polvijärvi</GeographicalUsage></ExampleCtn><ExampleCtn><Example style="normal">Hampun varsia
poltettiin tupakan puutteessa:<Citation style="dialect">liinav varrelaha ne polt ku ei muuta
olt.</Citation></Example><GeographicalUsage type="used" freeType="pitäjä">Juva</GeographicalUsage></ExampleCtn><ExampleCtn><Example style="normal"><Citation style="dialect">ehä ne pellaveesta nuottarihmoja kehrännää mut
liinosta.</Citation></Example><GeographicalUsage type="used" freeType="pitäjä">Ristiina</GeographicalUsage></ExampleCtn><ExampleCtn><Example style="normal"><Citation style="dialect">Pellavat pit ollam Mikom päivää, liinat miestempäivää</Citation>
mennessä puhdistettuina kehräämistä varten.</Example><GeographicalUsage type="used" freeType="pitäjä">Mäntyharju</GeographicalUsage></ExampleCtn><ExampleCtn><Example style="normal"><Citation style="dialect">Siinä
pikkasta enne juhannusta ne tavottaavatten tehäl liinasa</Citation>, tapaavat kylvää
hampun.</Example><GeographicalUsage type="used" freeType="pitäjä">Kangasniemi</GeographicalUsage></ExampleCtn><ExampleCtn><Example style="normal"><Citation style="dialect">niistä liinòenniis syvämmistä<Gloss>= hamppujenkin
aivinoista</Gloss>
kuvottiil<Gloss>pöytä</Gloss>liinoja.</Citation></Example><GeographicalUsage type="used" freeType="pitäjä">Jäppilä</GeographicalUsage></ExampleCtn><ExampleCtn><Example style="normal"><Citation style="dialect">Halamek
kasvo hyväl liinan.</Citation></Example><GeographicalUsage type="used" freeType="pitäjä">Vieremä</GeographicalUsage></ExampleCtn><ExampleCtn><Example style="normal"><Citation style="dialect">liinasta
ja pellavasta, vèikkoset, oĺ voatteet.</Citation></Example><GeographicalUsage type="used" freeType="pitäjä">Pihtipudas</GeographicalUsage></ExampleCtn><ExampleCtn><Example style="normal"><Citation style="dialect">nii
elläät sopu<sup>i</sup>sàst ko linnut liinàs</Citation><Gloss>=
hamppupellossa</Gloss> sp.</Example><GeographicalUsage type="used" freeType="pitäjä">Venjoki</GeographicalUsage></ExampleCtn><ExampleCtn><Example style="normal"><Citation style="dialect">a liinaa
meil ennää ei pietä<Gloss>= kasvateta</Gloss> ensikkää.</Citation></Example><GeographicalUsage type="used" freeType="pitäjä">Kallivere</GeographicalUsage></ExampleCtn></ExampleBlock><ExampleBlock><ExampleCtn><Example style="normal">Tuleentuneesta viljapellosta:<Citation style="dialect">Pelto on jo
liinalla.</Citation></Example><GeographicalUsage type="used" freeType="pitäjä">Kittilä</GeographicalUsage></ExampleCtn></ExampleBlock></SenseGrp><SenseGrp id="SMS_31db75415cdb4318c37e5965ea87f92d"><Definition>Linum usitatissimum, pellava.</Definition><Ptr style="kartta" xlink:href="98740"/><FreeTopic type="levikkitiedot">vanhoja
tietoja etenkin<GeographicalUsage type="used" freeType="alue" freeValue="eteläinen Varsinais-Suomi ja Länsi-Uusimaa">VarE-U</GeographicalUsage>.</FreeTopic><SeeAlsoBlock><SeeAlso style="Rinn"><Ptr xlink:href="SMS_6f8e1ed055374cde56cad4b3bfa28dad#SMS_dab77e55334cf2bb770798a3fee77a66" word="lina">lina<SenseNumber>2</SenseNumber></Ptr></SeeAlso></SeeAlsoBlock><ExampleBlock><ExampleCtn><Example style="normal"><Citation style="dialect">naapurin o liina nin kovì
lyhkäst.</Citation></Example><GeographicalUsage type="used" freeType="pitäjä">Suomusjärvi</GeographicalUsage></ExampleCtn><ExampleCtn><Example style="normal"><Citation style="dialect">Kun tuami kukòstaa sillon on liinan kylvön
aika.</Citation></Example><GeographicalUsage type="used" freeType="pitäjä">Nummi</GeographicalUsage></ExampleCtn><ExampleCtn><Example style="normal"><Citation style="dialect">Joks teirän on liinat veretty?</Citation></Example><GeographicalUsage type="used" freeType="pitäjä">Sammatti</GeographicalUsage></ExampleCtn><ExampleCtn><Example style="normal"><Citation style="dialect">liinoi
viätiin Helssinkiim mykyröittäi</Citation><Gloss>= 20 pivon nippuina</Gloss>
myytäväksi.</Example><GeographicalUsage type="used" freeType="pitäjä">Vihti</GeographicalUsage></ExampleCtn></ExampleBlock></SenseGrp><SenseGrp id="SMS_85d05912f5e158201169d45d3218be1f"><Definition><GrammaticalNumber freeValue="tav. mon." value="plural"/>: aivinat.</Definition><ExampleBlock><ExampleCtn><Example style="normal"><Citation style="dialect">hampu liinost
sitä̀ tehtin köyttä.</Citation> </Example><GeographicalUsage type="used" freeType="pitäjä">Suomusjärvi</GeographicalUsage></ExampleCtn><ExampleCtn><Example style="normal"><Citation style="dialect">Jos
se<Gloss>pellavapivo</Gloss> olì suur ni ne liinat heltisivä</Citation>
häkilöitäessä.</Example><GeographicalUsage type="used" freeType="pitäjä">Karjalohja</GeographicalUsage></ExampleCtn><ExampleCtn><Example style="normal">Laskiaismäessä huudetaan:<Citation style="dialect">lipsuu lapsuu liinaa, kasva pitkä
pellovas, muile ihmisile<span style="sparse">liinaa</span> jaakkolaisile tuppuroi
tappuroi!</Citation></Example><GeographicalUsage type="used" freeType="pitäjä">Uusikirkko Vpl.</GeographicalUsage></ExampleCtn></ExampleBlock></SenseGrp><SenseGrp id="SMS_63a8d31477d8fe72dfcaf4c9b60fccb8"><Definition>havupuussa kuoren ja puuaineksen välissä oleva aines,
jälsi.</Definition><Ptr style="kartta" xlink:href="98737"/><FreeTopic type="levikkitiedot"><GeographicalUsage type="used" freeType="alue" freeValue="Pohjois-Pohjanmaa">PohP</GeographicalUsage> osaksi,<GeographicalUsage type="used" freeType="alue" freeValue="Kainuu">Kai</GeographicalUsage> osaksi.</FreeTopic><ExampleBlock><ExampleCtn><Example style="normal"><Citation style="dialect">Liinasta tehtiim
pettuva.</Citation></Example><GeographicalUsage type="used" freeType="pitäjä">Muhos</GeographicalUsage></ExampleCtn><ExampleCtn><Example style="normal"><Citation style="dialect">puhas liina jeäpi ku silivit̆tää koarna ja se silipa
poes.</Citation></Example><GeographicalUsage type="used" freeType="pitäjä">Sotkamo</GeographicalUsage></ExampleCtn><ExampleCtn><Example style="normal"><Citation style="dialect">puusta otettiin sitä liinoa mahalan aekana.</Citation></Example><GeographicalUsage type="used" freeType="pitäjä">Puolanka</GeographicalUsage></ExampleCtn></ExampleBlock></SenseGrp><SenseGrp id="SMS_29ad8f74bc5979dce3e24bbbec121887"><Definition>palttinasidoksinen (pellava)kangas.</Definition><Ptr style="kartta" xlink:href="98739"/><FreeTopic type="levikkitiedot">eniten
tietoja<GeographicalUsage type="used" freeType="alue" freeValue="pohjoinen ja eteläinen Varsinais-Suomi sekä Varsinais-Suomen ylämaa">VarP-E-Y</GeographicalUsage><GeographicalUsage type="used" freeType="alue" freeValue="Satakunta">Sat</GeographicalUsage><GeographicalUsage type="used" freeType="alue" freeValue="Pohjanmaa">Poh</GeographicalUsage><GeographicalUsage type="used" freeType="alue" freeValue="Pohjois- ja Kaakkois-Häme">HämP-K</GeographicalUsage><GeographicalUsage type="used" freeType="alue" freeValue="läntinen Keski-Suomi">KesL</GeographicalUsage><GeographicalUsage type="used" freeType="alue" freeValue="Kainuu">Kai</GeographicalUsage><GeographicalUsage type="used" freeType="alue" freeValue="Länsipohja">LänP</GeographicalUsage>,
vähemmän<GeographicalUsage type="used" freeType="alue" freeValue="Etelä-Häme">HämE</GeographicalUsage><GeographicalUsage type="used" freeType="alue" freeValue="eteläinen Keski-Suomi">KesE</GeographicalUsage><GeographicalUsage type="used" freeType="alue" freeValue="Peräpohjola">PerP</GeographicalUsage>, lisäksi tietoja
liepeiltä.</FreeTopic><ExampleBlock><ExampleCtn><Example style="normal"><Citation style="dialect">Ko
riukhänt<Gloss>= västäräkki</Gloss> tulè<Gloss>keväällä, eivätkä
langat vielä ole kudottuina ja puut pilkottuina</Gloss> ni se laola: hyi
häp<Gloss>= häpeä</Gloss>, liina lankoin ja puu rankoin.</Citation></Example><GeographicalUsage type="used" freeType="pitäjä">Pyhäranta</GeographicalUsage></ExampleCtn><ExampleCtn><Example style="normal"><Citation style="dialect">Onkost
teijä ny liina kuttel?</Citation></Example><GeographicalUsage type="used" freeType="pitäjä">Laitila</GeographicalUsage></ExampleCtn><ExampleCtn><Example style="normal"><Citation style="dialect">Rohtimisest liinast tehti miähil aì heina<sub>)</sub>ajàks
rohtimisep pöksyk ko niitul mentti.</Citation></Example><GeographicalUsage type="used" freeType="pitäjä">Mynämäki</GeographicalUsage></ExampleCtn><ExampleCtn><Example style="normal"><Citation style="dialect">Sit ku
– – liina tulì valmiks ni sit pesètetti sit ja
tɛllɛttin ketto viäl pleikkantuma</Citation>,
valkaistumaan.</Example><GeographicalUsage type="used" freeType="pitäjä">Sauvo</GeographicalUsage></ExampleCtn><ExampleCtn><Example style="normal">Paitakangas<Citation style="dialect">ol liinam
pɛɛhɛn<Gloss>= kankaan loppuloimeen</Gloss>
kuròttu.</Citation></Example><GeographicalUsage type="used" freeType="pitäjä">Sauvo</GeographicalUsage></ExampleCtn><ExampleCtn><Example style="normal"><Citation style="dialect">eì stä saanul liinaks oìkeen noùsemaan ko pantiij järjestäns
niisiim mutta ko pantiir ristiniisiin ni se noùsi hyvìn.</Citation></Example><GeographicalUsage type="used" freeType="pitäjä">Vampula</GeographicalUsage></ExampleCtn><ExampleCtn><Example style="normal"><Citation style="dialect">se kehräs
liinal loimekkim pellovasta.</Citation></Example><GeographicalUsage type="used" freeType="pitäjä">Kauvatsa</GeographicalUsage></ExampleCtn><ExampleCtn><Example style="normal"><Citation style="dialect">Paita
itte oli liinaa, kivijalaka<Gloss>= paidan alaosa</Gloss>
hurstia.</Citation></Example><GeographicalUsage type="used" freeType="pitäjä">Lapua</GeographicalUsage></ExampleCtn><ExampleCtn><Example style="normal"><Citation style="dialect">Kymmenen kyynnärääkil löivät päivässä sitä
liinaa.</Citation></Example><GeographicalUsage type="used" freeType="pitäjä">Vesilahti</GeographicalUsage></ExampleCtn><ExampleCtn><Example style="normal"><Citation style="dialect">valakosesta liinasta paijat miehilläki.</Citation></Example><GeographicalUsage type="used" freeType="pitäjä">Keuruu</GeographicalUsage></ExampleCtn><ExampleCtn><Example style="normal"><Citation style="dialect">myytihil
liinaa<Gloss>= leikittiin erästä leikkiä</Gloss> niisä</Citation>
saunarakennuksissa.</Example><GeographicalUsage type="used" freeType="pitäjä">Himanka</GeographicalUsage></ExampleCtn><ExampleCtn><Example style="normal"><Citation style="dialect">niitä<Gloss>alusvaatteita</Gloss> tehtiil
liinasta<Gloss>= puuvillakankaasta</Gloss> ja niitä tehtiin àivan
tusinamäärällä.</Citation></Example><GeographicalUsage type="used" freeType="pitäjä">Ii</GeographicalUsage></ExampleCtn><ExampleCtn><Example style="normal"><Citation style="dialect">Se<Gloss>purje</Gloss> kun tämmösestä tavallisesta
liinasta tehhään.</Citation></Example><GeographicalUsage type="used" freeType="pitäjä">Utajärvi</GeographicalUsage></ExampleCtn><ExampleCtn><Example style="normal"><Citation style="dialect">liinoa
ee nähnyp paljo kirkkopàetana</Citation> sillä kirkossa oltiin rohdinkankaisissa
vaatteissa.</Example><GeographicalUsage type="used" freeType="pitäjä">Sotkamo</GeographicalUsage></ExampleCtn><ExampleCtn><Example style="normal"><Citation style="dialect">Se oli<Gloss>kymmenen</Gloss> kyynärää liinaa, vuessa
ja, ja kaksi kiloa villoja</Citation> mitä palvelija sai talosta.</Example><GeographicalUsage type="used" freeType="pitäjä">Pello</GeographicalUsage></ExampleCtn><ExampleCtn><Example style="normal"><Citation style="dialect">äiti vaina sitte osti punttilankoja, sitä̀
pumpulilankaa josta liinaa kuòthiin, ja kakstoista kyynärää räiväsi<Gloss>=
kutoi äkkiä</Gloss> liinaa.</Citation></Example><GeographicalUsage type="used" freeType="pitäjä">Kainulasjärvi</GeographicalUsage></ExampleCtn></ExampleBlock></SenseGrp><SenseGrp id="SMS_22f4a5042b1fcc8ea9df02e1fbeb3e2b"><Definition>ryhmään 5 liittyvää käyttöä.</Definition><SenseGrp id="SMS_90ce0c5134e771c18bb14fe1d1c42e35"><Definition>huivi.</Definition><Ptr style="kartta" xlink:href="98736"/><FreeTopic type="levikkitiedot"><GeographicalUsage type="used" freeType="alue" freeValue="pohjoinen Varsinais-Suomi ja Varsinais-Suomen ylämaa">VarP-Y</GeographicalUsage><GeographicalUsage type="used" freeType="alue" freeValue="Pohjois-Satakunta">SatP</GeographicalUsage><GeographicalUsage type="used" freeType="alue" freeValue="Häme">Häm</GeographicalUsage><GeographicalUsage type="used" freeType="alue" freeValue="Kymenlaakso ja Itä-Uusimaa">Kym</GeographicalUsage>,<GeographicalUsage type="used" freeType="alue" freeValue="pohjoinen Keski-Suomi">KesP</GeographicalUsage> osaksi,<GeographicalUsage type="used" freeType="alue" freeValue="eteläinen Keski-Suomi">KesE</GeographicalUsage>, lisäksi
tietoja liepeiltä.</FreeTopic><ExampleBlock><ExampleCtn><Example style="normal">Emäntä oli kadonnut jäljettömiin, vain<Citation style="dialect">liin ol
haràvalavàs</Citation> heinäpellolla.</Example><GeographicalUsage type="used" freeType="pitäjä">Hinnerjoki</GeographicalUsage></ExampleCtn><ExampleCtn><Example style="normal"><Citation style="dialect">Talvel
pirètti villassi liinoi.</Citation></Example><GeographicalUsage type="used" freeType="pitäjä">Taivassalo</GeographicalUsage></ExampleCtn><ExampleCtn><Example style="normal"><Citation style="dialect">eìkä
pesny mun totà liinatan.</Citation></Example><GeographicalUsage type="used" freeType="pitäjä">Sauvo</GeographicalUsage></ExampleCtn><ExampleCtn><Example style="normal"><Citation style="dialect">Naisil
olì pääsä vallal liinoi ja miähil olì lippulakkei.</Citation></Example><GeographicalUsage type="used" freeType="pitäjä">Somero</GeographicalUsage></ExampleCtn><ExampleCtn><Example style="normal">Kun
alettiin kirnuta<Citation style="dialect">täyty kovastis sitoop puhras liina</Citation>
päähän.</Example><GeographicalUsage type="used" freeType="pitäjä">Urjala</GeographicalUsage></ExampleCtn><ExampleCtn><Example style="normal"><Citation style="dialect">Ja min
em mitään kotsaa<Gloss>= hattua</Gloss> päähäni pa, jos ̮emma
liinalla kelpaa, nin se on se sama.</Citation></Example><GeographicalUsage type="used" freeType="pitäjä">Akaa</GeographicalUsage></ExampleCtn><ExampleCtn><Example style="normal"><Citation style="dialect">Kaulas
ne ja ruukas liinaa.</Citation></Example><GeographicalUsage type="used" freeType="pitäjä">Hausjärvi</GeographicalUsage></ExampleCtn><ExampleCtn><Example style="normal"><Citation style="dialect">valakosia liinoja kä̀yttivät</Citation> naiset
ennen.</Example><GeographicalUsage type="used" freeType="pitäjä">Joutsa</GeographicalUsage></ExampleCtn><ExampleCtn><Example style="normal"><Citation style="dialect">liinan ne aina vet piähä, jos ei muuten ne vet
piällaelle</Citation>.</Example><GeographicalUsage type="used" freeType="pitäjä">Hartola</GeographicalUsage></ExampleCtn><ExampleCtn><Example style="normal"><Citation style="dialect">mummu
ei tykänny<Gloss>että solmin huivin niskaan</Gloss> ja sano: jokos sinä
taas pistit liinas kupparilleen.</Citation></Example><GeographicalUsage type="used" freeType="pitäjä">Keuruu</GeographicalUsage></ExampleCtn></ExampleBlock></SenseGrp><SenseGrp id="SMS_c288b976cfc0c22de638a53ff5a3fef2"><Definition>muista kangaskappaleista.</Definition><ExampleBlock><ExampleCtn><Example style="normal"><Citation style="dialect">Rikkaak kannettiin omilla
liinollaa</Citation> hautaan.</Example><GeographicalUsage type="used" freeType="pitäjä">Längelmäki</GeographicalUsage></ExampleCtn><ExampleCtn><Example style="normal"><Citation style="dialect">valkonel
liina siä polvilaurallaki</Citation> oli ehtoollispöydän edessä.</Example><GeographicalUsage type="used" freeType="pitäjä">Urjala</GeographicalUsage></ExampleCtn><ExampleCtn><Example style="normal"><Citation style="dialect">keäriet
làitettiin<Gloss>kuumetautiselle</Gloss> niinko kapalovyöt teält, villain
liina.</Citation></Example><GeographicalUsage type="used" freeType="pitäjä">Padasjoki</GeographicalUsage></ExampleCtn><ExampleCtn><Example style="normal"><Citation style="dialect">pàestirrasvoa rä̀eskäht liinalle.</Citation></Example><GeographicalUsage type="used" freeType="pitäjä">Konginkangas</GeographicalUsage></ExampleCtn><ExampleCtn><Example style="normal"><Citation style="dialect">nep
pani valakial liinan semmosem pitkän saiton<Gloss>= riu'un</Gloss>
nokkaha</Citation> ja pyydystivät sillä lepakoita.</Example><GeographicalUsage type="used" freeType="pitäjä">Himanka</GeographicalUsage></ExampleCtn><ExampleCtn><Example style="normal">Ruumislaudalla makaavalle vainajalle pannaan liina silmille, ja
siksi sanottiin:<Citation style="dialect">ei täsä tiejäl liina pääsä ruveta ojottahan
kuolemaa.</Citation></Example><GeographicalUsage type="used" freeType="pitäjä">Himanka</GeographicalUsage></ExampleCtn><ExampleCtn><Example style="normal">Tavan mukaan<Citation style="dialect">valakonen liina<Gloss><SeeAlso style="Vrt"><Ptr xlink:href="SMS_383897dc20cfebbec42e19281593521b" word="luokkiliina">luokkiliina</Ptr></SeeAlso></Gloss> oli hevosen valjaissa</Citation>
kun ruumista vietiin hautaan.</Example><GeographicalUsage type="used" freeType="pitäjä">Puolanka</GeographicalUsage></ExampleCtn><ExampleCtn><Example style="normal"><Citation style="dialect">länsilestaatiolaiset ne om pitä̀nhet syntinä
nästyykit, että korèutta s ̮oom pittää liinoja, pakkarissakhan</Citation>,
taskussakaan.</Example><GeographicalUsage type="used" freeType="pitäjä">Kainulasjärvi</GeographicalUsage></ExampleCtn></ExampleBlock></SenseGrp></SenseGrp><SenseGrp id="SMS_1471c6b7c2b5bcab0c3a84e1847b2951"><Definition>ehtoollispöytä; ehtoollispöydällinen; ehtoollisella käymisestä:
käydä<HiddenEntryGrp><Headword freeType="alihakusana">liinalla</Headword></HiddenEntryGrp>.</Definition><Ptr style="kartta" xlink:href="98734"/><FreeTopic type="levikkitiedot">eniten
tietoja<GeographicalUsage type="used" freeType="alue" freeValue="Varsinais-Suomi">Var</GeographicalUsage><GeographicalUsage type="used" freeType="alue" freeValue="Etelä-Pohjanmaa">PohE</GeographicalUsage><GeographicalUsage type="used" freeType="alue" freeValue="Vermlanti">Ver</GeographicalUsage>, vähemmän<GeographicalUsage type="used" freeType="alue" freeValue="Pohjois-Satakunta">SatP</GeographicalUsage><GeographicalUsage type="used" freeType="alue" freeValue="Pohjois-Häme">HämP</GeographicalUsage><GeographicalUsage type="used" freeType="alue" freeValue="Pohjois-Savo">SavP</GeographicalUsage><GeographicalUsage type="used" freeType="alue" freeValue="pohjoinen Keski-Suomi">KesP</GeographicalUsage><GeographicalUsage type="used" freeType="alue" freeValue="Keski-Pohjanmaa">PohK</GeographicalUsage><GeographicalUsage type="used" freeType="alue" freeValue="Kainuu">Kai</GeographicalUsage><GeographicalUsage type="used" freeType="alue" freeValue="Peräpohjola">PerP</GeographicalUsage>, lisäksi tietoja
liepeiltä.</FreeTopic><SeeAlsoBlock><SeeAlso style="Vrt"><Ptr xlink:href="SMS_edd7425646d7d482239dc42956a7eb70#SMS_d827c341a617d4d586e16a0588c2db84" word="lauta:1">lauta<HomographNumber>1</HomographNumber><SenseNumber>4.b</SenseNumber></Ptr><Ptr xlink:href="SMS_7a73fbe7cb28cfbec9bb0adcd89f5bcb" word="liinalauta">liinalauta</Ptr><Ptr xlink:href="SMS_0ef5515ceda8da39dd4a6b4a70de0f26" word="liinallinen">liinallinen</Ptr><Ptr xlink:href="SMS_da546e6fe1f824ec1226244736ee650f" word="liinap%C3%B6yt%C3%A4">liinapöytä</Ptr></SeeAlso></SeeAlsoBlock><ExampleBlock><ExampleCtn><Example style="normal"><Citation style="dialect">kyl se liin täyn
ol.</Citation></Example><GeographicalUsage type="used" freeType="pitäjä">Hinnerjoki</GeographicalUsage></ExampleCtn><ExampleCtn><Example style="normal"><Citation style="dialect">Miähe
menivä ensi liinal ja vast ko kaik miähe oliva ollu nii sit menivä
naise.</Citation></Example><GeographicalUsage type="used" freeType="pitäjä">Karjala Tl.</GeographicalUsage></ExampleCtn><ExampleCtn><Example style="normal"><Citation style="dialect">ku mɛ sit siit liinalt penkkim
pɛɛsi</Citation> toisten auttamana, olin aivan uuvuksissa.</Example><GeographicalUsage type="used" freeType="pitäjä">Sauvo</GeographicalUsage></ExampleCtn><ExampleCtn><Example style="normal"><Citation style="dialect">mää menev
vasta toiseel liinaa.</Citation></Example><GeographicalUsage type="used" freeType="pitäjä">Vihti</GeographicalUsage></ExampleCtn><ExampleCtn><Example style="normal"><Citation style="dialect">Rippilapsii oli nii paljo, ettei mahtunu yhtee
liinaa.</Citation></Example><GeographicalUsage type="used" freeType="pitäjä">Ulvila</GeographicalUsage></ExampleCtn><ExampleCtn><Example style="normal"><Citation style="dialect">Se<Gloss>tyttö</Gloss> nym menis aiva
entteliä<Gloss>= väkisin</Gloss> hyppyyhiv<Gloss>=
tansseihin</Gloss> vaikkei oov vielä liinallakaak käyny.</Citation></Example><GeographicalUsage type="used" freeType="pitäjä">Jalasjärvi</GeographicalUsage></ExampleCtn><ExampleCtn><Example style="normal"><Citation style="dialect">minä
lählim poih<Gloss>kirkosta</Gloss> kun ruvettiil liinalla
käymeen.</Citation></Example><GeographicalUsage type="used" freeType="pitäjä">Hämeenkyrö</GeographicalUsage></ExampleCtn><ExampleCtn><Example style="normal"><Citation style="dialect">kut toinel liina mennee pois niin toinen astuu
tilalle.</Citation></Example><GeographicalUsage type="used" freeType="pitäjä">Orivesi</GeographicalUsage></ExampleCtn><ExampleCtn><Example style="normal"><Citation style="dialect">siellä oĺ kuus liinoo seorakuntoo.</Citation></Example><GeographicalUsage type="used" freeType="pitäjä">Maaninka</GeographicalUsage></ExampleCtn><ExampleCtn><Example style="normal">Ikää
kysytään:<Citation style="dialect">joko se ol liinalla kä̀öpä?</Citation></Example><GeographicalUsage type="used" freeType="pitäjä">Konginkangas</GeographicalUsage></ExampleCtn><ExampleCtn><Example style="normal"><Citation style="dialect">Minä
olin sen kansa samalla liinalla.</Citation></Example><GeographicalUsage type="used" freeType="pitäjä">Sievi</GeographicalUsage></ExampleCtn><ExampleCtn><Example style="normal"><Citation style="dialect">oliko
montakil liin̆naa rippiväkijä?</Citation></Example><GeographicalUsage type="used" freeType="pitäjä">Nivala</GeographicalUsage></ExampleCtn><ExampleCtn><Example style="normal"><Citation style="dialect">ne
mehtämiehet käv liinalla teällä.</Citation></Example><GeographicalUsage type="used" freeType="pitäjä">Vermlanti</GeographicalUsage></ExampleCtn></ExampleBlock></SenseGrp><SenseGrp id="SMS_dbc29eb85504cb93fe62f2ab6bbf2fb3"><Definition>kalanpyydyksen verkkokudos, havas.</Definition><Ptr style="kartta" xlink:href="98738"/><FreeTopic type="levikkitiedot">eniten
tietoja<GeographicalUsage type="used" freeType="alue" freeValue="pohjoinen Varsinais-Suomi ja Länsi-Uusimaa">VarP-U</GeographicalUsage><GeographicalUsage type="used" freeType="alue" freeValue="Länsi- ja Pohjois-Satakunta">SatL-P</GeographicalUsage><GeographicalUsage type="used" freeType="alue" freeValue="Pohjois- ja Kaakkois-Häme">HämP-K</GeographicalUsage><GeographicalUsage type="used" freeType="alue" freeValue="Kymenlaakso ja Itä-Uusimaa">Kym</GeographicalUsage><GeographicalUsage type="used" freeType="alue" freeValue="Savo">Sav</GeographicalUsage><GeographicalUsage type="used" freeType="alue" freeValue="Keski-Suomi ">Kes</GeographicalUsage><GeographicalUsage type="used" freeType="alue" freeValue="Keski- ja Pohjois-Pohjanmaa">PohK-P</GeographicalUsage><GeographicalUsage type="used" freeType="alue" freeValue="Kainuu">Kai</GeographicalUsage><GeographicalUsage type="used" freeType="alue" freeValue="Peräpohjola">PerP</GeographicalUsage><GeographicalUsage type="used" freeType="alue" freeValue="Länsipohja">LänP</GeographicalUsage>,
vähemmän<GeographicalUsage type="used" freeType="alue" freeValue="Etelä- ja Pohjois-Karjala">KarE-P</GeographicalUsage>, lisäksi tietoja
liepeiltä.</FreeTopic><SeeAlsoBlock><SeeAlso style="Rinn"><Ptr xlink:href="SMS_d647b0f9dd52ae7316e771e1a4f86683#SMS_0345b4a4c9acba6e771fc30b115c5633" word="liinu">liinu<SenseNumber>3</SenseNumber></Ptr><GeographicalUsage type="used" freeType="pitäjä">Ahlainen</GeographicalUsage><Ptr xlink:href="SMS_6f8e1ed055374cde56cad4b3bfa28dad#SMS_8d057762cf20e5927e5aec57e3c6771b" word="lina">lina<SenseNumber>1</SenseNumber></Ptr></SeeAlso></SeeAlsoBlock><ExampleBlock><ExampleCtn><Example style="normal"><Citation style="dialect">Siin
̮ol<Gloss>nuotassa</Gloss> liina niim pali et siin ̮ol
sitteki vetä̀mist.</Citation></Example><GeographicalUsage type="used" freeType="pitäjä">Eurajoki</GeographicalUsage></ExampleCtn><ExampleCtn><Example style="normal"><Citation style="dialect">Se olì
aika hiano<Gloss>= tiheäsilmäinen</Gloss> liina et sihèn ̮istus
särkiki kiini.</Citation></Example><GeographicalUsage type="used" freeType="pitäjä">Karjalohja</GeographicalUsage></ExampleCtn><ExampleCtn><Example style="normal"><Citation style="dialect">Mnul
olis tual kaks verkol liinaa ko tarttis paulottaa.</Citation></Example><GeographicalUsage type="used" freeType="pitäjä">Ahlainen</GeographicalUsage></ExampleCtn><ExampleCtn><Example style="normal"><Citation style="dialect">Em minä
ymmärräk kuinka se tosta liinan keskeltä veletään se nialun suu että se
luannikas tullee.</Citation></Example><GeographicalUsage type="used" freeType="pitäjä">Teisko</GeographicalUsage></ExampleCtn><ExampleCtn><Example style="normal"><Citation style="dialect">loppu
otettii sitte käsirysil<Gloss>= käsin</Gloss>, uittaja lappo vaa sitä
liinaa</Citation> nuotanvedon viime vaiheessa.</Example><GeographicalUsage type="used" freeType="pitäjä">Seiskari</GeographicalUsage></ExampleCtn><ExampleCtn><Example style="normal"><Citation style="dialect">Tulii
halavemmaks kum pisteä ihte aenat liinoihi.</Citation></Example><GeographicalUsage type="used" freeType="pitäjä">Jämsä</GeographicalUsage></ExampleCtn><ExampleCtn><Example style="normal">Hän on
lähtenyt vetämään nuottaa:<Citation style="dialect">se nyt om mennyt vetämhän liinaa.</Citation></Example><GeographicalUsage type="used" freeType="pitäjä">Jyykeä</GeographicalUsage></ExampleCtn><ExampleCtn><Example style="normal"><Citation style="dialect">Se on
niinku tämäv verram pitkältä sitä liinaa, sitä pussia siinä</Citation>
lipossa.</Example><GeographicalUsage type="used" freeType="pitäjä">Karunki</GeographicalUsage></ExampleCtn></ExampleBlock><ExampleBlock><ExampleCtn><Example style="normal"><Citation style="dialect">ne<Gloss>verkot</Gloss> olliit kaks liinaa pitkii,
liin o kuuskyment metrii.</Citation></Example><GeographicalUsage type="used" freeType="pitäjä">Uusikirkko Vpl.</GeographicalUsage></ExampleCtn><ExampleCtn><Example style="normal"><Citation style="dialect">verkossa levvyys sehä̀n se ol liina.</Citation></Example><GeographicalUsage type="used" freeType="pitäjä">Kainulasjärvi</GeographicalUsage></ExampleCtn></ExampleBlock></SenseGrp></DictionaryEntry><DictionaryEntry id="SMS_fdb3cef81af2b3cc9401178afb2f2b79" homographNumber="2" style="normaali"><HeadwordCtn><Headword>liina</Headword><SearchForm display="no">liina</SearchForm><PartOfSpeechCtn><PartOfSpeech freeValue="s."/></PartOfSpeechCtn></HeadwordCtn><Definition>köysi.</Definition><Ptr style="kartta" xlink:href="98743"/><p style="kappaleenvaihto"/><FreeTopic type="levikkitiedot">joitakin
tietoja<GeographicalUsage type="used" freeType="alue" freeValue="eteläinen Varsinais-Suomi ja Länsi-Uusimaa">VarE-U</GeographicalUsage><GeographicalUsage type="used" freeType="alue" freeValue="Pohjois- ja Etelä-Häme">HämP-E</GeographicalUsage><GeographicalUsage type="used" freeType="alue" freeValue="Kymenlaakso ja Itä-Uusimaa">Kym</GeographicalUsage><GeographicalUsage type="used" freeType="alue" freeValue="Etelä-Karjala">KarE</GeographicalUsage> ja liepeiltä, lisäksi
yksittäistietoja.</FreeTopic><ExampleBlock><ExampleCtn><Example style="normal"><Citation style="dialect">hevonev veti
liinoist<Gloss>= kakkula-aisojen aisoina käytettävistä
köysistä</Gloss></Citation> heinäkonetta.</Example><GeographicalUsage type="used" freeType="pitäjä">Vihti</GeographicalUsage></ExampleCtn><ExampleCtn><Example style="normal"><Citation style="dialect">Mää
hellitin äkkiä sen aisan alas ja hellitil liinat,
heitin<Gloss>hevosen</Gloss> seljäm päällej ja lährim menemään</Citation>
ukkosta pakoon.</Example><GeographicalUsage type="used" freeType="pitäjä">Tammela</GeographicalUsage></ExampleCtn><ExampleCtn><Example style="normal"><Citation style="dialect">vahva sinkkiliina</Citation>, vaijeri.</Example><GeographicalUsage type="used" freeType="pitäjä">Kymi</GeographicalUsage></ExampleCtn><ExampleCtn><Example style="normal"><Citation style="dialect">Liina<Gloss>= ankkuriköysi</Gloss> potkitaa</Citation>,
soudetaan kauemmaksi.</Example><GeographicalUsage type="used" freeType="pitäjä">Valkeala</GeographicalUsage></ExampleCtn></ExampleBlock></DictionaryEntry><DictionaryEntry id="SMS_1a6c8364cb665e1c1f089d230e9ccde2" homographNumber="3" style="normaali"><HeadwordCtn><Headword>liina</Headword><SearchForm display="no">liina</SearchForm><PartOfSpeechCtn><PartOfSpeech freeValue="s."/></PartOfSpeechCtn></HeadwordCtn><Definition>pitkäsiima.</Definition><Ptr style="kartta" xlink:href="98744"/><p style="kappaleenvaihto"/><ExampleBlock><ExampleCtn><Example style="normal"><Citation style="dialect">Ne<Gloss>muualta
tulleet kalastajat</Gloss> on tulleet sieltä liinoinneen
päivinneen.</Citation></Example><GeographicalUsage type="used" freeType="pitäjä">Vesisaari</GeographicalUsage></ExampleCtn><ExampleCtn><Example style="normal"><Citation style="dialect">liinala tullee vielä muitakik
kaloja, affenia ja matheja.</Citation></Example><GeographicalUsage type="used" freeType="pitäjä">Vesisaari</GeographicalUsage></ExampleCtn><ExampleCtn><Example style="normal"><Citation style="dialect">Liina
seisooki niin kauan nyt lähemä vetämhän sen.</Citation></Example><GeographicalUsage type="used" freeType="pitäjä">Raisi</GeographicalUsage></ExampleCtn><ExampleCtn><Example/><GeographicalUsage type="used" freeType="pitäjä">Jyykeä</GeographicalUsage></ExampleCtn></ExampleBlock></DictionaryEntry><DictionaryEntry id="SMS_b00aa486817a2b9ea187d158d585472f" style="normaali"><HeadwordCtn><Headword>liina|aitaus</Headword><SearchForm display="no">liinaaitaus</SearchForm><Word display="no" type="compound"><Prefix>liina</Prefix><Stem>aitaus</Stem></Word><PartOfSpeechCtn><PartOfSpeech freeValue="s."/></PartOfSpeechCtn></HeadwordCtn><Definition>alttarista.</Definition><p style="kappaleenvaihto"/><SeeAlsoBlock><SeeAlso style="Vrt"><Ptr xlink:href="SMS_cde11c876d7bdb608430670f9191605d#SMS_1471c6b7c2b5bcab0c3a84e1847b2951" word="liina:1">liina<HomographNumber>1</HomographNumber><SenseNumber>7</SenseNumber></Ptr></SeeAlso></SeeAlsoBlock><ExampleBlock><ExampleCtn><Example style="normal"><Citation style="citation">Liina-aitaus.</Citation></Example><GeographicalUsage type="used" freeType="pitäjä">Nilsiä</GeographicalUsage></ExampleCtn></ExampleBlock></DictionaryEntry><DictionaryEntry id="SMS_1d4f252ab27e80d2fe0cfbb4e930708b" style="normaali"><HeadwordCtn><Headword>liina|-aivina</Headword><SearchForm display="no">liina-aivina</SearchForm><Word display="no" type="compound"><Prefix>liina</Prefix><Stem>aivina</Stem></Word><PartOfSpeechCtn><PartOfSpeech freeValue="s."/></PartOfSpeechCtn></HeadwordCtn><Definition>hampun,<SeeAlso style="TakanViite"><Ptr xlink:href="SMS_cde11c876d7bdb608430670f9191605d#SMS_251482ecb7ff30682e778beb3231f7bb" word="liina:1">liinan<HomographNumber>1</HomographNumber><SenseNumber>1</SenseNumber></Ptr></SeeAlso>,
aivina.</Definition><p style="kappaleenvaihto"/><ExampleBlock><ExampleCtn><Example style="normal"><Citation style="dialect">Miehillen tehtii hòusuja ja pàetoja àevinasta tehtiil
liina<Hyphen>₍</Hyphen>àevinasta.</Citation></Example><GeographicalUsage type="used" freeType="pitäjä">Leppävirta</GeographicalUsage></ExampleCtn></ExampleBlock></DictionaryEntry><DictionaryEntry id="SMS_fade195bacc0a4e3769c144993842689" style="normaali"><HeadwordCtn><Headword>liina|-alusta</Headword><SearchForm display="no">liina-alusta</SearchForm><Word display="no" type="compound"><Prefix>liina</Prefix><Stem>alusta</Stem></Word><PartOfSpeechCtn><PartOfSpeech freeValue="s."/></PartOfSpeechCtn></HeadwordCtn><p style="kappaleenvaihto"/><ExampleBlock><ExampleCtn><Example style="normal"><Citation style="dialect">ne ennel
liina<Hyphen>₍</Hyphen>alustakki<Gloss>= pellavasta kudotut aluslakanat</Gloss>
lyötihin kaikki hangelle</Citation> valkenemaan.</Example><GeographicalUsage type="used" freeType="pitäjä">Himanka</GeographicalUsage></ExampleCtn></ExampleBlock></DictionaryEntry><DictionaryEntry id="SMS_dff676d60f589e541e90c2d505b1871a" style="normaali"><HeadwordCtn><Headword>liina|halme</Headword><SearchForm display="no">liinahalme</SearchForm><Word display="no" type="compound"><Prefix>liina</Prefix><Stem>halme</Stem></Word><PartOfSpeechCtn><PartOfSpeech freeValue="s."/></PartOfSpeechCtn></HeadwordCtn><Definition>hamppupelto.</Definition><p style="kappaleenvaihto"/><ExampleBlock><ExampleCtn><Example style="normal"><Citation style="dialect">Tihheetä kun liinahalame.</Citation></Example><GeographicalUsage type="used" freeType="pitäjä">Lapinlahti</GeographicalUsage></ExampleCtn></ExampleBlock></DictionaryEntry><DictionaryEntry id="SMS_a19aea9457b2913be457f40828d4c1e3" style="normaali"><HeadwordCtn><Headword>liina|harja</Headword><SearchForm display="no">liinaharja</SearchForm><Word display="no" type="compound"><Prefix>liina</Prefix><Stem>harja</Stem></Word><PartOfSpeechCtn><PartOfSpeech freeValue="n."/></PartOfSpeechCtn></HeadwordCtn><p style="kappaleenvaihto"/><SenseGrp id="SMS_6cdb07ec34b8742d795b3ae4b73307d6"><Definition>vaaleaharjaisesta ja -häntäisestä hevosesta: liinakko; hevosen
vaaleasta harjasta.</Definition><SeeAlsoBlock><SeeAlso style="Vrt"><Ptr xlink:href="SMS_0983a79df0bb1d2b46bd805b62955e5e" word="liinaharjahevonen">liinaharjahevonen</Ptr><Ptr xlink:href="SMS_d0dd5b3665d3efde964c799cba67844e" word="liinahevonen">liinahevonen</Ptr><Ptr xlink:href="SMS_baf812406b5d80e6ce2be45c4ff5db88" word="liinah%C3%A4nt%C3%A4">liinahäntä</Ptr></SeeAlso></SeeAlsoBlock><ExampleBlock><ExampleCtn><Example style="normal"><Citation style="dialect">hevoshuijjari ol
myinyˀ yheleˀ iham mitättömäl liinaharjaj joka piti viijjäh heti
rapahautaa</Citation>, tappaa ja haudata metsään.</Example><GeographicalUsage type="used" freeType="pitäjä">Keuruu</GeographicalUsage></ExampleCtn><ExampleCtn><Example style="normal"><Citation style="dialect">se<Gloss>hevonen</Gloss> onki oikein komia joka on
tummar rauvikko ja jolla ol liinaharija.</Citation></Example><GeographicalUsage type="used" freeType="pitäjä">Himanka</GeographicalUsage></ExampleCtn><ExampleCtn><Example style="normal"><Citation style="dialect">liinaharja hepone on Suomen toukkuu</Citation>, sukua.</Example><GeographicalUsage type="used" freeType="pitäjä">Kallivere</GeographicalUsage></ExampleCtn></ExampleBlock><ExampleBlock><ExampleCtn><Example style="normal">Arv.:<Citation style="dialect">pikkulintu liinaharja läpi seinäl lentelee</Citation> (neula
ja lanka).</Example><GeographicalUsage type="used" freeType="pitäjä">Hattula</GeographicalUsage></ExampleCtn></ExampleBlock></SenseGrp><SenseGrp id="SMS_98fdb97b0664b6de792955ca9b3a0e99"><Definition>vaaleatukkaisesta.</Definition><ExampleBlock><ExampleCtn><Example style="normal"><Citation style="dialect">sellail liinaharja laiha
likka.</Citation></Example><GeographicalUsage type="used" freeType="pitäjä">Padasjoki</GeographicalUsage></ExampleCtn><ExampleCtn><Example style="normal"><Citation style="dialect">N ̮om meirän sikiät<Gloss>= lapset</Gloss>
sellasia liinaharjoja.</Citation></Example><GeographicalUsage type="used" freeType="pitäjä">Kaustinen</GeographicalUsage></ExampleCtn></ExampleBlock></SenseGrp><SenseGrp id="SMS_365ef38f65c5cbef5ad4eccf531c06a2"><Definition>pellava- t. hamppuharja.</Definition><ExampleBlock><ExampleCtn><Example style="normal"><Citation style="dialect">Liinaharjal harjattii ku
oli häkìlöity, niinku silkkii vaa</Citation> tuli langasta.</Example><GeographicalUsage type="used" freeType="pitäjä">Sammatti</GeographicalUsage></ExampleCtn></ExampleBlock></SenseGrp></DictionaryEntry><DictionaryEntry id="SMS_0983a79df0bb1d2b46bd805b62955e5e" style="normaali"><HeadwordCtn><Headword>liina|harja|hevonen</Headword><SearchForm display="no">liinaharjahevonen</SearchForm><Word display="no" type="compound"><Prefix>liina|harja</Prefix><Stem>hevonen</Stem></Word><PartOfSpeechCtn><PartOfSpeech freeValue="s."/></PartOfSpeechCtn></HeadwordCtn><Definition>vaaleaharjainen ja -häntäinen hevonen, liinakko.</Definition><p style="kappaleenvaihto"/><ExampleBlock><ExampleCtn><Example style="normal"><Citation style="dialect">ne olliit samallaisii
liinaharjahevosii mitä hyö käyttiit paris ain.</Citation></Example><GeographicalUsage type="used" freeType="pitäjä">Uusikirkko Vpl.</GeographicalUsage></ExampleCtn></ExampleBlock></DictionaryEntry><DictionaryEntry id="SMS_a4158e200984889067b002db6eb50c00" style="normaali"><HeadwordCtn><Headword>liina|harjainen</Headword><SearchForm display="no">liinaharjainen</SearchForm><Word display="no" type="compound"><Prefix>liina</Prefix><Stem>harjainen</Stem></Word><PartOfSpeechCtn><PartOfSpeech freeValue="a."/></PartOfSpeechCtn></HeadwordCtn><Definition>vaaleaharjainen.</Definition><p style="kappaleenvaihto"/><ExampleBlock><ExampleCtn><Example style="normal"><Citation style="dialect">se on tuonna markkinasta liinaharjaśeh
hevośen.</Citation></Example><GeographicalUsage type="used" freeType="pitäjä">Maaninka</GeographicalUsage></ExampleCtn></ExampleBlock></DictionaryEntry><DictionaryEntry id="SMS_8a221722b118676cd196d60d4d71953f" style="normaali"><HeadwordCtn><Headword>liina|heikki</Headword><SearchForm display="no">liinaheikki</SearchForm><Word display="no" type="compound"><Prefix>liina</Prefix><Stem>heikki</Stem></Word><PartOfSpeechCtn><PartOfSpeech freeValue="s."/></PartOfSpeechCtn></HeadwordCtn><Definition>Nymphaea, lumme.</Definition><Ptr style="kartta" xlink:href="98745"/><p style="kappaleenvaihto"/><SeeAlsoBlock><SeeAlso style="Vrt"><Ptr xlink:href="SMS_634ca2319bbf2e26440bcb8f9550ff30" word="liinakukka">liinakukka</Ptr></SeeAlso></SeeAlsoBlock><ExampleBlock><ExampleCtn><Example/><GeographicalUsage type="used" freeType="pitäjä">Pyhäjärvi Ol.</GeographicalUsage></ExampleCtn><ExampleCtn><Example style="normal"><Citation style="dialect">liinaheikki.</Citation></Example><GeographicalUsage type="used" freeType="pitäjä">Nivala</GeographicalUsage></ExampleCtn><ExampleCtn><Example/><GeographicalUsage type="used" freeType="pitäjä">Kärsämäki</GeographicalUsage></ExampleCtn></ExampleBlock></DictionaryEntry><DictionaryEntry id="SMS_7879bd2203818c905759a3311b160185" style="normaali"><HeadwordCtn><Headword>liina|herra</Headword><SearchForm display="no">liinaherra</SearchForm><Word display="no" type="compound"><Prefix>liina</Prefix><Stem>herra</Stem></Word><PartOfSpeechCtn><PartOfSpeech freeValue="s."/></PartOfSpeechCtn></HeadwordCtn><Definition>Nymphaea, lumme.</Definition><Ptr style="kartta" xlink:href="98746"/><p style="kappaleenvaihto"/><SeeAlsoBlock><SeeAlso style="Vrt"><Ptr xlink:href="SMS_634ca2319bbf2e26440bcb8f9550ff30" word="liinakukka">liinakukka</Ptr></SeeAlso></SeeAlsoBlock><ExampleBlock><ExampleCtn><Example/><GeographicalUsage type="used" freeType="pitäjä">Oulainen</GeographicalUsage></ExampleCtn><ExampleCtn><Example/><GeographicalUsage type="used" freeType="pitäjä">Pattijoki</GeographicalUsage></ExampleCtn><ExampleCtn><Example style="normal"><Citation style="dialect">Liinaherra.</Citation></Example><GeographicalUsage type="used" freeType="pitäjä">Vihanti</GeographicalUsage></ExampleCtn></ExampleBlock></DictionaryEntry><DictionaryEntry id="SMS_d0dd5b3665d3efde964c799cba67844e" style="normaali"><HeadwordCtn><Headword>liina|hevonen</Headword><SearchForm display="no">liinahevonen</SearchForm><Word display="no" type="compound"><Prefix>liina</Prefix><Stem>hevonen</Stem></Word><PartOfSpeechCtn><PartOfSpeech freeValue="s."/></PartOfSpeechCtn></HeadwordCtn><p style="kappaleenvaihto"/><ExampleBlock><ExampleCtn><Example style="normal"><Citation style="dialect">oli
liinahevonen<Gloss>= liinakko</Gloss> sillä.</Citation></Example><GeographicalUsage type="used" freeType="pitäjä">Ii</GeographicalUsage></ExampleCtn></ExampleBlock></DictionaryEntry><DictionaryEntry id="SMS_a7c75646e3a44424d4e25daeebc2695d" style="normaali"><HeadwordCtn><Headword>liina|hirsi</Headword><SearchForm display="no">liinahirsi</SearchForm><Word display="no" type="compound"><Prefix>liina</Prefix><Stem>hirsi</Stem></Word><PartOfSpeechCtn><PartOfSpeech freeValue="s."/></PartOfSpeechCtn></HeadwordCtn><Definition>jk tuvan katossa sivuseinästä toiseen kulkeva
hirsi.</Definition><Ptr style="kartta" xlink:href="98747"/><p style="kappaleenvaihto"/><ExampleBlock><ExampleCtn><Example/><GeographicalUsage type="used" freeType="pitäjä">Vilppula</GeographicalUsage></ExampleCtn><ExampleCtn><Example/><GeographicalUsage type="used" freeType="pitäjä">Kuorevesi</GeographicalUsage></ExampleCtn><ExampleCtn><Example/><GeographicalUsage type="used" freeType="pitäjä">Jämsä</GeographicalUsage></ExampleCtn><ExampleCtn><Example style="normal"><Citation style="citation">Pääsiäiseksi tehtiin usein köysistä pirtin liinahirteen
keilu<Gloss>= keinu</Gloss> pienemmille lapsille.</Citation></Example><GeographicalUsage type="used" freeType="pitäjä">Koskenpää</GeographicalUsage></ExampleCtn></ExampleBlock></DictionaryEntry><DictionaryEntry id="SMS_bda30b884d9d145647272f58ef027e63" style="normaali"><HeadwordCtn><Headword>liina|housu</Headword><SearchForm display="no">liinahousu</SearchForm><Word display="no" type="compound"><Prefix>liina</Prefix><Stem>housu</Stem></Word><PartOfSpeechCtn><PartOfSpeech freeValue="s."/></PartOfSpeechCtn></HeadwordCtn><Definition><GrammaticalNumber freeValue="tav. mon." value="plural"/>: hamppuiset t. pellavaiset
(alus)housut.</Definition><p style="kappaleenvaihto"/><ExampleBlock><ExampleCtn><Example style="normal"><Citation style="dialect">kun sill ̮ol<Gloss>hollimiehellä</Gloss>
valkoset liinahousut niin seh hiärty pers</Citation> kun joutui palaamaan
kyytiajosta ratsastaen.</Example><GeographicalUsage type="used" freeType="pitäjä">Kymi</GeographicalUsage></ExampleCtn><ExampleCtn><Example style="normal"><Citation style="dialect">Kuka
käski lähtee liinahousussaan<Gloss>= vähissä vaatteissa</Gloss> nousovaan
Jumalan ilimaan?</Citation></Example><GeographicalUsage type="used" freeType="pitäjä">Maaninka</GeographicalUsage></ExampleCtn><ExampleCtn><Example style="normal"><Citation style="dialect">lapsena
juoksivattii sillä liinahòusulla.</Citation></Example><GeographicalUsage type="used" freeType="pitäjä">Vehmersalmi</GeographicalUsage></ExampleCtn><ExampleCtn><Example style="normal"><Citation style="dialect">Kahet
liinahousut ja kaks riihmekkova kujottiir renkille ennen.</Citation></Example><GeographicalUsage type="used" freeType="pitäjä">Sysmä</GeographicalUsage></ExampleCtn></ExampleBlock></DictionaryEntry><DictionaryEntry id="SMS_34baf8e2cfe9391b922ead6bd190f3f1" style="normaali"><HeadwordCtn><Headword>liinahtava</Headword><SearchForm display="no">liinahtava</SearchForm><PartOfSpeechCtn><PartOfSpeech freeValue="a."/></PartOfSpeechCtn></HeadwordCtn><Definition>hevosesta t. sen harjasta: vaaleahko.</Definition><p style="kappaleenvaihto"/><ExampleBlock><ExampleCtn><Example style="normal">Hevosella on<Citation style="dialect">liinahtava
harija.</Citation></Example><GeographicalUsage type="used" freeType="pitäjä">Nurmo</GeographicalUsage></ExampleCtn><ExampleCtn><Example style="normal"><Citation style="dialect">semmonel liinahtava se<Gloss>hevonen</Gloss>
oĺ.</Citation></Example><GeographicalUsage type="used" freeType="pitäjä">Kitee</GeographicalUsage></ExampleCtn></ExampleBlock></DictionaryEntry><DictionaryEntry id="SMS_31242fe16a6bf41835a986f3f7d29c0a" style="normaali"><HeadwordCtn><Headword>liina|huhta</Headword><SearchForm display="no">liinahuhta</SearchForm><Word display="no" type="compound"><Prefix>liina</Prefix><Stem>huhta</Stem></Word><PartOfSpeechCtn><PartOfSpeech freeValue="s."/></PartOfSpeechCtn></HeadwordCtn><Definition>hamppupelto.</Definition><p style="kappaleenvaihto"/><ExampleBlock><ExampleCtn><Example style="normal"><Citation style="dialect">se on niin tih̆hee när̆rèikkö kul
liinahuuhta.</Citation></Example><GeographicalUsage type="used" freeType="pitäjä">Kiihtelysvaara</GeographicalUsage></ExampleCtn></ExampleBlock></DictionaryEntry><DictionaryEntry id="SMS_baf812406b5d80e6ce2be45c4ff5db88" style="normaali"><HeadwordCtn><Headword>liina|häntä</Headword><SearchForm display="no">liinahäntä</SearchForm><Word display="no" type="compound"><Prefix>liina</Prefix><Stem>häntä</Stem></Word><PartOfSpeechCtn><PartOfSpeech freeValue="n."/></PartOfSpeechCtn></HeadwordCtn><Definition>vaaleahäntäisestä hevosesta: liinakko.</Definition><p style="kappaleenvaihto"/><ExampleBlock><ExampleCtn><Example style="normal"><Citation style="dialect">eikos teitill
̮ennen kotoo ollul liinahäntä tamma?</Citation></Example><GeographicalUsage type="used" freeType="pitäjä">Iitti</GeographicalUsage></ExampleCtn><ExampleCtn><Example style="normal"><Citation style="dialect">liinahäntä.</Citation></Example><GeographicalUsage type="used" freeType="pitäjä">Kallivere</GeographicalUsage></ExampleCtn></ExampleBlock><ExampleBlock><ExampleCtn><Example style="normal">Arv.:<Citation style="dialect">Pikkulintu liinahäntä läpi seinän lentelee</Citation> (neula
ja lanka).</Example><GeographicalUsage type="used" freeType="pitäjä">Pirkkala</GeographicalUsage></ExampleCtn></ExampleBlock></DictionaryEntry><DictionaryEntry id="SMS_6c84dd174c5d3f6398ded8f27fcf91e0" style="normaali"><HeadwordCtn><Headword>liina|ihminen</Headword><SearchForm display="no">liinaihminen</SearchForm><Word display="no" type="compound"><Prefix>liina</Prefix><Stem>ihminen</Stem></Word><PartOfSpeechCtn><PartOfSpeech freeValue="s."/></PartOfSpeechCtn></HeadwordCtn><p style="kappaleenvaihto"/><SeeAlsoBlock><SeeAlso style="Vrt"><Ptr xlink:href="SMS_cde11c876d7bdb608430670f9191605d#SMS_1471c6b7c2b5bcab0c3a84e1847b2951" word="liina:1">liina<HomographNumber>1</HomographNumber><SenseNumber>7</SenseNumber></Ptr></SeeAlso></SeeAlsoBlock><ExampleBlock><ExampleCtn><Example style="normal"><Citation style="dialect">lukkar kirjuttaa
kirkonkammarissa liina<Hyphen>₍</Hyphen>imeiset<Gloss>= ehtoollisvieraat</Gloss>
ylös.</Citation></Example><GeographicalUsage type="used" freeType="pitäjä">Vermlanti</GeographicalUsage></ExampleCtn></ExampleBlock></DictionaryEntry><DictionaryEntry id="SMS_7bfac5b6938f38ba4e5431632d7e5a05" style="normaali"><HeadwordCtn><Headword>liinainen</Headword><SearchForm display="no">liinainen</SearchForm><PartOfSpeechCtn><PartOfSpeech freeValue="n."/></PartOfSpeechCtn></HeadwordCtn><p style="kappaleenvaihto"/><SenseGrp id="SMS_9233d58c5e11cda98f3f2e61d366a788"><Definition>hamppuinen, hamppukankainen; hamppukangas.</Definition><Ptr style="kartta" xlink:href="98749"/><FreeTopic type="levikkitiedot">tietoja<GeographicalUsage type="used" freeType="alue" freeValue="Pohjois-Karjala">KarP</GeographicalUsage><GeographicalUsage type="used" freeType="alue" freeValue="Savo">Sav</GeographicalUsage><GeographicalUsage type="used" freeType="alue" freeValue="pohjoinen Keski-Suomi">KesP</GeographicalUsage> ja liepeiltä, lisäksi<GeographicalUsage type="used" freeType="pitäjä">Venjoki</GeographicalUsage>.</FreeTopic><ExampleBlock><ExampleCtn><Example style="normal"><Citation style="dialect">Liinane köys ei olt hyvä, se vetty ja tuĺ
raskaaks.</Citation></Example><GeographicalUsage type="used" freeType="pitäjä">Ruokolahti</GeographicalUsage></ExampleCtn><ExampleCtn><Example style="normal">Jokin palaa:<Citation style="dialect">ihan tiällä ol liina<sup>i</sup>seh<Gloss>=
hamppukankaan</Gloss> haju.</Citation></Example><GeographicalUsage type="used" freeType="pitäjä">Kiihtelysvaara</GeographicalUsage></ExampleCtn><ExampleCtn><Example style="normal"><Citation style="dialect">liinasiahan ne oĺ järestää alusvoatteet
sitten.</Citation></Example><GeographicalUsage type="used" freeType="pitäjä">Viitasaari</GeographicalUsage></ExampleCtn><ExampleCtn><Example style="normal"><Citation style="dialect">ne hamput ol pitkiä – – niistä kehrättii sitte
ja liinasia täkkiä tekvät mitä panvat olokii peälles sänkyisä.</Citation></Example><GeographicalUsage type="used" freeType="pitäjä">Joutsa</GeographicalUsage></ExampleCtn><ExampleCtn><Example style="normal"><Citation style="dialect">kuottii liinasii kankait</Citation> joista tehtiin miehille
housuja.</Example><GeographicalUsage type="used" freeType="pitäjä">Venjoki</GeographicalUsage></ExampleCtn></ExampleBlock></SenseGrp><SenseGrp id="SMS_a1c9e91f832a760c47d856e3ce806990"><Definition>pellavainen (t. puuvillainen); aivinainen;
pellavakangas.</Definition><Ptr style="kartta" xlink:href="98750"/><FreeTopic type="levikkitiedot">eniten
tietoja<GeographicalUsage type="used" freeType="alue" freeValue="pohjoinen Varsinais-Suomi">VarP</GeographicalUsage><GeographicalUsage type="used" freeType="alue" freeValue="Etelä-Pohjanmaa">PohE</GeographicalUsage><GeographicalUsage type="used" freeType="alue" freeValue="Kaakkois-Häme">HämK</GeographicalUsage><GeographicalUsage type="used" freeType="alue" freeValue="Kymenlaakso ja Itä-Uusimaa">Kym</GeographicalUsage>.</FreeTopic><ExampleBlock><ExampleCtn><Example style="normal"><Citation style="dialect">puhta liinase vaatten kastin kylmä̀ vette ja
– – oikkem piukka se siihe<Gloss>haavan päälle</Gloss>
sitte, tälläsi.</Citation></Example><GeographicalUsage type="used" freeType="pitäjä">Eurajoki</GeographicalUsage></ExampleCtn><ExampleCtn><Example style="normal"><Citation style="dialect">ei
se<Gloss>väri</Gloss> ottannut<Gloss>= tarttunut</Gloss> taas toho
liinaisee.</Citation></Example><GeographicalUsage type="used" freeType="pitäjä">Vihti</GeographicalUsage></ExampleCtn><ExampleCtn><Example style="normal"><Citation style="dialect">pantiir rohtimisìa vaatteita alleppäij ja liinasia
päälle</Citation> pesusaaviin.</Example><GeographicalUsage type="used" freeType="pitäjä">Vampula</GeographicalUsage></ExampleCtn><ExampleCtn><Example style="normal"><Citation style="dialect">Parahinta
liinaasta mulla oli rustooslakanat</Citation>, kapiolakanat.</Example><GeographicalUsage type="used" freeType="pitäjä">Kuortane</GeographicalUsage></ExampleCtn><ExampleCtn><Example style="normal"><Citation style="dialect">Täm
̮on oikeel liinaasta liinaa.</Citation></Example><GeographicalUsage type="used" freeType="pitäjä">Kurikka</GeographicalUsage></ExampleCtn><ExampleCtn><Example style="normal"><Citation style="dialect">sehän<Gloss>sarka</Gloss> oli semmosta, liinaset
loimet ja villanen kule.</Citation></Example><GeographicalUsage type="used" freeType="pitäjä">Orivesi</GeographicalUsage></ExampleCtn><ExampleCtn><Example style="normal"><Citation style="dialect">lämmim
paita liinanenkin oman äiren ompelema, vilu ov vaippa villanenkiv vaimov
viarahan tekemä</Citation> sp.</Example><GeographicalUsage type="used" freeType="pitäjä">Hattula</GeographicalUsage></ExampleCtn><ExampleCtn><Example style="normal"><Citation style="dialect">liinain
ol sellai vilpoin, mie tein leninkinkii liinasest.</Citation></Example><GeographicalUsage type="used" freeType="pitäjä">Myrskylä</GeographicalUsage></ExampleCtn><ExampleCtn><Example style="normal"><Citation style="dialect">kankaat
tehtiin kaikki ite, liinaset ja mitä oli.</Citation></Example><GeographicalUsage type="used" freeType="pitäjä">Lehtimäki</GeographicalUsage></ExampleCtn></ExampleBlock></SenseGrp><SenseGrp id="SMS_02d9310277177fee2a85a695d5b3670f"><Definition><GrammaticalNumber freeValue="tav. mon." value="plural"/>: pellavan kuidut.</Definition><Ptr style="kartta" xlink:href="98751"/><ExampleBlock><ExampleCtn><Example style="normal"><Citation style="dialect">Nyt ruvetahan
liinaasihin</Citation>, pellavia käsittelemään.</Example><GeographicalUsage type="used" freeType="pitäjä">Isokyrö</GeographicalUsage></ExampleCtn><ExampleCtn><Example/><GeographicalUsage type="used" freeType="pitäjä">Kuortane</GeographicalUsage></ExampleCtn><ExampleCtn><Example style="normal"><Citation style="dialect">Pitääs
jo ruvetal liinaasijakik keheräämähän.</Citation></Example><GeographicalUsage type="used" freeType="pitäjä">Kurikka</GeographicalUsage></ExampleCtn></ExampleBlock></SenseGrp><SenseGrp id="SMS_4cb42e254a1beec9ed88c70fc64aa98f"><Definition><HiddenEntryGrp><Headword freeType="alihakusana">liinaisillaan</Headword></HiddenEntryGrp> = alusvaatteisillaan,
paitasillaan.</Definition><ExampleBlock><ExampleCtn><Example style="normal"><Citation style="dialect">liina<sup>i</sup>sillaan se männöö sàonaan.</Citation></Example><GeographicalUsage type="used" freeType="pitäjä">Konginkangas</GeographicalUsage></ExampleCtn><ExampleCtn><Example style="normal"><Citation style="dialect">on niir
rasvatyyni, lämmin, tarkenoo aevan liinasillaan.</Citation></Example><GeographicalUsage type="used" freeType="pitäjä">Ristijärvi</GeographicalUsage></ExampleCtn></ExampleBlock></SenseGrp></DictionaryEntry><DictionaryEntry id="SMS_539cbfc770f106219e14fa13d43c20df" style="normaali"><HeadwordCtn><Headword>liinais|loiminen</Headword><SearchForm display="no">liinaisloiminen</SearchForm><Word display="no" type="compound"><Prefix>liinais</Prefix><Stem>loiminen</Stem></Word><PartOfSpeechCtn><PartOfSpeech freeValue="a."/></PartOfSpeechCtn></HeadwordCtn><p style="kappaleenvaihto"/><ExampleBlock><ExampleCtn><Example style="normal"><Citation style="dialect">Liinaahloimistakis<Gloss>= puuvillaloimistakin</Gloss>
sarkaa teherähän.</Citation></Example><GeographicalUsage type="used" freeType="pitäjä">Kauhajoki</GeographicalUsage></ExampleCtn></ExampleBlock></DictionaryEntry><DictionaryEntry id="SMS_f43d9d683e2df270736f2af4c4c3a904" style="normaali"><HeadwordCtn><Headword>liina|kahlo</Headword><SearchForm display="no">liinakahlo</SearchForm><Word display="no" type="compound"><Prefix>liina</Prefix><Stem>kahlo</Stem></Word><PartOfSpeechCtn><PartOfSpeech freeValue="s."/></PartOfSpeechCtn></HeadwordCtn><Definition>pellavista sidottu iso lyhde.</Definition><p style="kappaleenvaihto"/><ExampleBlock><ExampleCtn><Example style="normal"><Citation style="dialect">liinkahlo.</Citation></Example><GeographicalUsage type="used" freeType="pitäjä">Perniö</GeographicalUsage></ExampleCtn></ExampleBlock></DictionaryEntry><DictionaryEntry id="SMS_bcc917968ae8c416dd9812d80141a7cb" style="normaali"><HeadwordCtn><Headword>liina|kangas</Headword><SearchForm display="no">liinakangas</SearchForm><Word display="no" type="compound"><Prefix>liina</Prefix><Stem>kangas</Stem></Word><PartOfSpeechCtn><PartOfSpeech freeValue="s."/></PartOfSpeechCtn></HeadwordCtn><Definition>pellava- t. hamppukangas.</Definition><p style="kappaleenvaihto"/><ExampleBlock><ExampleCtn><Example style="normal"><Citation style="dialect">Palttinata oĺ
<Gloss>alus</Gloss>paijaˀ yläosa ja liinakangasta
alaosa.</Citation></Example><GeographicalUsage type="used" freeType="pitäjä">Sumiainen</GeographicalUsage></ExampleCtn></ExampleBlock></DictionaryEntry><DictionaryEntry id="SMS_ddaea296cf9fc1326d818820fa6784e6" style="normaali"><HeadwordCtn><Headword>liina|kerros</Headword><SearchForm display="no">liinakerros</SearchForm><Word display="no" type="compound"><Prefix>liina</Prefix><Stem>kerros</Stem></Word><PartOfSpeechCtn><PartOfSpeech freeValue="s."/></PartOfSpeechCtn></HeadwordCtn><p style="kappaleenvaihto"/><ExampleBlock><ExampleCtn><Example style="normal"><Citation style="dialect">Kaarnun<Gloss>=
kaarnan</Gloss> alla ol liinakerros<Gloss>=
jälsikerros,<SeeAlso style="TakanViite"><Ptr xlink:href="SMS_cde11c876d7bdb608430670f9191605d#SMS_63a8d31477d8fe72dfcaf4c9b60fccb8" word="liina:1">liina
<HomographNumber>1</HomographNumber><SenseNumber>4</SenseNumber></Ptr></SeeAlso></Gloss> josta kehittyy vuotunen syvi</Citation>,
vuosikasvu.</Example><GeographicalUsage type="used" freeType="pitäjä">Muhos</GeographicalUsage></ExampleCtn></ExampleBlock></DictionaryEntry></Dictionary>